wordle_manager/__init__.py
wordle_manager/cli.py
wordle_manager/main.py
wordle_manager/utils.py
wordle_manager/words.py
wordle_words-0.3.0.dist-info/METADATA
wordle_words-0.3.0.dist-info/WHEEL
wordle_words-0.3.0.dist-info/entry_points.txt
wordle_words-0.3.0.dist-info/licenses/LICENSE
wordle_words-0.3.0.dist-info/RECORD
