Metadata-Version: 2.4
Name: wordle-words
Version: 0.3.0
Summary: Package for generating Wordle words
Author-email: Nicholas Carsner <nicholascarsner@gmail.com>
License-File: LICENSE
Requires-Python: >=3.13
